odoo/addons/product_variant_route_mto/README.rst
odoo/addons/product_variant_route_mto/__init__.py
odoo/addons/product_variant_route_mto/__manifest__.py
odoo/addons/product_variant_route_mto/i18n/it.po
odoo/addons/product_variant_route_mto/i18n/product_variant_route_mto.pot
odoo/addons/product_variant_route_mto/models/__init__.py
odoo/addons/product_variant_route_mto/models/product_product.py
odoo/addons/product_variant_route_mto/models/product_template.py
odoo/addons/product_variant_route_mto/readme/CONFIGURATION.md
odoo/addons/product_variant_route_mto/readme/CONTRIBUTORS.md
odoo/addons/product_variant_route_mto/readme/CREDITS.md
odoo/addons/product_variant_route_mto/readme/DESCRIPTION.md
odoo/addons/product_variant_route_mto/static/description/icon.png
odoo/addons/product_variant_route_mto/static/description/index.html
odoo/addons/product_variant_route_mto/tests/__init__.py
odoo/addons/product_variant_route_mto/tests/common.py
odoo/addons/product_variant_route_mto/tests/test_mto_variant.py
odoo/addons/product_variant_route_mto/views/product_product.xml
odoo_addon_product_variant_route_mto-18.0.1.0.1.dist-info/METADATA
odoo_addon_product_variant_route_mto-18.0.1.0.1.dist-info/WHEEL
odoo_addon_product_variant_route_mto-18.0.1.0.1.dist-info/top_level.txt
odoo_addon_product_variant_route_mto-18.0.1.0.1.dist-info/RECORD
